{"frames":{"character5.png":{"frame":{"x":4,"y":4,"w":595,"h":657},"rotated":false,"trimmed":true,"spriteSourceSize":{"x":1,"y":2,"w":595,"h":657},"sourceSize":{"w":600,"h":660},"pivot":{"x":0.5,"y":0.5}},"character6.png":{"frame":{"x":607,"y":4,"w":631,"h":509},"rotated":false,"trimmed":true,"spriteSourceSize":{"x":13,"y":0,"w":631,"h":509},"sourceSize":{"w":644,"h":509},"pivot":{"x":0.5,"y":0.5}},"character1.png":{"frame":{"x":4,"y":669,"w":585,"h":403},"rotated":false,"trimmed":true,"spriteSourceSize":{"x":0,"y":0,"w":585,"h":403},"sourceSize":{"w":586,"h":406},"pivot":{"x":0.5,"y":0.5}},"character2.png":{"frame":{"x":4,"y":1080,"w":464,"h":556},"rotated":false,"trimmed":true,"spriteSourceSize":{"x":0,"y":1,"w":464,"h":556},"sourceSize":{"w":464,"h":560},"pivot":{"x":0.5,"y":0.5}},"character3.png":{"frame":{"x":476,"y":1080,"w":373,"h":378},"rotated":false,"trimmed":true,"spriteSourceSize":{"x":4,"y":4,"w":373,"h":378},"sourceSize":{"w":382,"h":384},"pivot":{"x":0.5,"y":0.5}},"character4.png":{"frame":{"x":857,"y":521,"w":357,"h":368},"rotated":false,"trimmed":false,"spriteSourceSize":{"x":0,"y":0,"w":357,"h":368},"sourceSize":{"w":357,"h":368},"pivot":{"x":0.5,"y":0.5}},"logo_ball.png":{"frame":{"x":476,"y":1466,"w":113,"h":113},"rotated":false,"trimmed":true,"spriteSourceSize":{"x":0,"y":0,"w":113,"h":113},"sourceSize":{"w":113,"h":114},"pivot":{"x":0.5,"y":0.5}},"logo_ball_shadow.png":{"frame":{"x":597,"y":1466,"w":104,"h":91},"rotated":false,"trimmed":true,"spriteSourceSize":{"x":1,"y":23,"w":104,"h":91},"sourceSize":{"w":113,"h":114},"pivot":{"x":0.5,"y":0.5}},"button-unlockables-notification.png":{"frame":{"x":476,"y":1587,"w":41,"h":40},"rotated":false,"trimmed":true,"spriteSourceSize":{"x":3,"y":4,"w":41,"h":40},"sourceSize":{"w":47,"h":47},"pivot":{"x":0.5,"y":0.5}},"notify-dot-red.png":{"frame":{"x":525,"y":1587,"w":34,"h":34},"rotated":false,"trimmed":false,"spriteSourceSize":{"x":0,"y":0,"w":34,"h":34},"sourceSize":{"w":34,"h":34},"pivot":{"x":0.5,"y":0.5}}},"meta":{"app":"http://github.com/odrick/free-tex-packer-core","version":"0.1.9","image":"home.png","format":"RGBA8888","size":{"w":1242,"h":1640},"scale":1}}