[1,0,0,[["cc.AnimationClip",["_name","_duration","curveData"],1,11]],[[0,0,1,2,3]],[[0,"anim_chp_award",1.5833333333333333,[{},"paths",11,[{"itemList":{"props":{"active":[{"frame":0,"value":false},{"frame":0.75,"value":true}]}},"info":{"props":{"opacity":[{"frame":0,"value":0},{"frame":1.5,"value":0},{"frame":1.5833333333333333,"value":125}]}},"close_node":{"comps":{},"props":{"active":[{"frame":0,"value":false},{"frame":1.5,"value":true}]}}},"cup",11,[{},"props",11,[{"opacity":[{"frame":0.36666666666666664,"value":0},{"frame":0.4666666666666667,"value":255}]},"scale",12,[[[{"frame":0},"value",8,[0,0,0]],[{"frame":0.36666666666666664},"value",8,[0,0.9,0.9]],[{"frame":0.4666666666666667},"value",8,[0,1,1]],[{"frame":0.6},"value",8,[0,1.1,0.9]],[{"frame":0.7833333333333333},"value",8,[0,0.92,1.2]],[{"frame":0.8666666666666667},"value",8,[0,1.05,0.98]],[{"frame":0.9166666666666666},"value",8,[0,1,1]]],11,11,11,11,11,11,11]]]]]]],0,0,[],[],[]]