{"add":[{"type":"GEM_RANDOM","x":3,"y":7},{"type":"GEM_RANDOM","x":4,"y":7},{"type":"GEM_RANDOM","x":5,"y":7},{"type":"GEM_RANDOM","x":1,"y":6},{"type":"GEM_RANDOM","x":2,"y":6},{"type":"GEM_RANDOM","x":3,"y":6},{"type":"GEM_RANDOM","x":4,"y":6},{"type":"GEM_RANDOM","x":5,"y":6},{"type":"GEM_RANDOM","x":6,"y":6},{"type":"GEM_RANDOM","x":7,"y":6},{"type":"GEM_RANDOM","x":1,"y":5},{"type":"GEM_RANDOM","x":2,"y":5},{"type":"GROUP_SINGLE_HIT_EACH","x":3,"y":5},{"type":"GROUP_SINGLE_HIT_EACH","x":4,"y":5},{"type":"GROUP_SINGLE_HIT_EACH","x":5,"y":5},{"type":"GEM_RANDOM","x":6,"y":5},{"type":"GEM_RANDOM","x":7,"y":5},{"type":"COCONUT","x":0,"y":4},{"type":"GEM_RANDOM","x":1,"y":4},{"type":"GROUP_SINGLE_HIT_EACH2","x":2,"y":4},{"type":"GROUP_SINGLE_HIT_EACH2","x":3,"y":4},{"type":"GEM_RANDOM","x":4,"y":4},{"type":"GROUP_SINGLE_HIT_EACH2","x":5,"y":4},{"type":"GROUP_SINGLE_HIT_EACH2","x":6,"y":4},{"type":"GEM_RANDOM","x":7,"y":4},{"type":"COCONUT","x":8,"y":4},{"type":"COCONUT","x":0,"y":3},{"type":"GROUP_SINGLE_HIT_EACH","x":1,"y":3},{"type":"GROUP_SINGLE_HIT_EACH","x":2,"y":3},{"type":"GEM_RANDOM","x":3,"y":3},{"type":"GEM_RANDOM","x":4,"y":3},{"type":"GEM_RANDOM","x":5,"y":3},{"type":"GROUP_SINGLE_HIT_EACH","x":6,"y":3},{"type":"GROUP_SINGLE_HIT_EACH","x":7,"y":3},{"type":"COCONUT","x":8,"y":3},{"type":"COCONUT","x":0,"y":2},{"type":"COCONUT","x":1,"y":2},{"type":"GEM_RANDOM","x":2,"y":2},{"type":"GEM_RANDOM","x":3,"y":2},{"type":"FERTILIZER","x":4,"y":2},{"type":"GEM_RANDOM","x":5,"y":2},{"type":"GEM_RANDOM","x":6,"y":2},{"type":"COCONUT","x":7,"y":2},{"type":"COCONUT","x":8,"y":2},{"type":"COCONUT","x":0,"y":1},{"type":"COCONUT","x":1,"y":1},{"type":"GROUP_SINGLE_HIT_EACH2","x":2,"y":1},{"type":"GROUP_SINGLE_HIT_EACH2","x":3,"y":1},{"type":"GEM_RANDOM","x":4,"y":1},{"type":"GROUP_SINGLE_HIT_EACH2","x":5,"y":1},{"type":"GROUP_SINGLE_HIT_EACH2","x":6,"y":1},{"type":"COCONUT","x":7,"y":1},{"type":"COCONUT","x":8,"y":1},{"type":"GROUP_SINGLE_HIT_EACH2","x":2,"y":0},{"type":"GROUP_SINGLE_HIT_EACH","x":3,"y":0},{"type":"GROUP_SINGLE_HIT_EACH","x":4,"y":0},{"type":"GROUP_SINGLE_HIT_EACH","x":5,"y":0},{"type":"GROUP_SINGLE_HIT_EACH2","x":6,"y":0}],"sizeX":9,"score":5992.898684210526,"size":8,"field":["oooxxxooo","oxxxxxxxo","oxxxxxxxo","xxxxxxxxx","xxxxxxxxx","xxxxxxxxx","xxxxxxxxx","ooxxxxxoo"],"allowedGemTypes":["GEM_RED","GEM_GREEN","GEM_WHITE"],"moves":25,"version":1,"sizeY":8,"tasks":[{"type":"GROUP_SINGLE_HIT_EACH","count":8},{"type":"FERTILIZER","count":1},{"type":"COCONUT","count":12}],"ratio":0.42236842105263156}