{"type":"View","props":{"width":750,"runtime":"script/views/uis/CeremonyView.ts","height":1334},"compId":2,"child":[{"type":"Box","props":{"var":"background","top":0,"right":0,"left":0,"bottom":0},"compId":10},{"type":"Box","props":{"width":1,"height":1,"centerX":0},"compId":9,"child":[{"type":"Animation","props":{"y":0,"x":0,"var":"ceremonyAni","source":"animation/scene_change.ani"},"compId":8}]},{"type":"Label","props":{"width":231,"height":26,"fontSize":26,"color":"#ffffff","centerX":0,"bottom":215,"anchorY":0.5,"anchorX":0.5,"align":"left"},"compId":12},{"type":"Label","props":{"y":5,"x":0,"visible":false,"var":"txtVersion","text":"v1.0.00","right":20,"leading":5,"fontSize":22,"color":"#ffffff","anchorY":0,"anchorX":1,"alpha":0.7},"compId":17},{"type":"Label","props":{"y":33,"x":0,"visible":false,"var":"txtUid","text":"uid:123456","right":20,"fontSize":22,"color":"#ffffff","anchorY":0,"anchorX":1,"alpha":0.7},"compId":18}],"animations":[{"nodes":[{"target":12,"keyframes":{"alpha":[{"value":0,"tweenMethod":"linearNone","tween":true,"target":12,"key":"alpha","index":0},{"value":0,"tweenMethod":"linearNone","tween":true,"target":12,"key":"alpha","index":6},{"value":1,"tweenMethod":"linearNone","tween":true,"target":12,"key":"alpha","index":16}]}}],"name":"show_ui","id":1,"frameRate":24,"action":0},{"nodes":[{"target":12,"keyframes":{"alpha":[{"value":1,"tweenMethod":"linearNone","tween":true,"target":12,"key":"alpha","index":0},{"value":0,"tweenMethod":"linearNone","tween":true,"target":12,"key":"alpha","index":6}]}}],"name":"close_ui","id":1,"frameRate":24,"action":0},{"nodes":[{"target":12,"keyframes":{"width":[{"value":160,"tweenMethod":"linearNone","tween":true,"target":12,"key":"width","index":0}],"text":[{"value":"Room cleaning.","tweenMethod":"linearNone","tween":false,"target":12,"key":"text","index":0},{"value":"Room cleaning..","tweenMethod":"linearNone","tween":false,"target":12,"key":"text","index":12},{"value":"Room cleaning...","tweenMethod":"linearNone","tween":false,"target":12,"key":"text","index":24},{"value":"","tweenMethod":"linearNone","tween":false,"target":12,"label":null,"key":"text","index":36}],"alpha":[{"value":1,"tweenMethod":"linearNone","tween":true,"target":12,"key":"alpha","index":0}]}}],"name":"room_loading","id":2,"frameRate":24,"action":0},{"nodes":[{"target":12,"keyframes":{"width":[{"value":231,"tweenMethod":"linearNone","tween":true,"target":12,"key":"width","index":0},{"value":230,"tweenMethod":"linearNone","tween":true,"target":12,"key":"width","index":36}],"text":[{"value":"","tweenMethod":"linearNone","tween":false,"target":12,"key":"text","index":0},{"value":"","tweenMethod":"linearNone","tween":false,"target":12,"key":"text","index":12},{"value":"","tweenMethod":"linearNone","tween":false,"target":12,"key":"text","index":24},{"value":"","tweenMethod":"linearNone","tween":false,"target":12,"label":null,"key":"text","index":36}],"alpha":[{"value":1,"tweenMethod":"linearNone","tween":true,"target":12,"key":"alpha","index":0}]}}],"name":"fb_loading","id":2,"frameRate":24,"action":0}],"loadList":["animation/scene_change.ani"],"loadList3D":[]}