{"type":"Box","props":{"y":0,"x":0,"width":750,"runtime":"script/views/uis/PlayerBox.ts","presetID":1,"isPresetRoot":true,"height":74,"centerX":0},"compId":138,"child":[{"type":"Image","props":{"y":46,"x":52,"width":88,"skin":"ui/img_circlebar1.png","presetID":2,"name":"imgLevelBg","height":88,"anchorY":0.5,"anchorX":0.5},"compId":110,"child":[{"type":"Animation","props":{"y":44,"x":44,"source":"animation/light_blue.ani","presetID":22,"name":"lightExp","autoPlay":true},"compId":146},{"type":"Image","props":{"y":44,"x":44,"skin":"ui/img_circlebar3.png","runtime":"script/common/CircleProgress.ts","presetID":19,"name":"levelBar","centerY":0,"centerX":0,"anchorY":0.5,"anchorX":0.5},"compId":143},{"type":"Image","props":{"skin":"ui/img_circlebar2.png","presetID":18,"centerY":0,"centerX":0,"anchorY":0.5,"anchorX":0.5},"compId":142},{"type":"Image","props":{"skin":"ui/icon_36_4_2.png","scaleY":1.2,"scaleX":1.2,"presetID":4,"name":"imgExp","centerY":0,"centerX":3,"anchorY":0.5,"anchorX":0.5},"compId":109,"child":[{"type":"Label","props":{"width":34,"valign":"middle","text":"4","strokeColor":"#cb3f19","stroke":3,"presetID":5,"name":"txtLevel","height":31,"fontSize":32,"color":"#ffffff","centerY":0,"centerX":-6,"bold":true,"anchorY":0.5,"anchorX":0.5,"align":"center"},"compId":120}]}]},{"type":"Image","props":{"y":22,"x":111,"width":130,"skin":"ui/bg_exp.png","sizeGrid":"20,25,20,27","presetID":6,"name":"imgPowerBg","height":47},"compId":113,"child":[{"type":"Image","props":{"y":27,"x":18,"skin":"ui/icon_22_4_1.png","presetID":7,"name":"imgPower","anchorY":0.5,"anchorX":0.5},"compId":112},{"type":"Label","props":{"valign":"middle","text":"88","strokeColor":"#cb3f19","stroke":2,"presetID":8,"name":"txtPower","fontSize":28,"color":"#FFF","centerY":0,"centerX":11,"bold":true,"anchorY":0.5,"anchorX":0.5,"align":"center"},"compId":126},{"type":"Label","props":{"visible":false,"valign":"middle","text":"00:00","strokeColor":"#cb3f19","stroke":2,"presetID":9,"name":"txtPowerTime","fontSize":20,"color":"#fbc029","centerY":21,"centerX":12,"bold":true,"anchorY":0.5,"anchorX":0.5,"align":"center"},"compId":127},{"type":"Image","props":{"visible":false,"skin":"ui/bt_add.png","scaleY":0.4,"scaleX":0.4,"presetID":21,"name":"btnAddPower","centerY":17,"centerX":-42,"anchorY":0.5,"anchorX":0.5},"compId":145}]},{"type":"Image","props":{"y":21,"x":270,"width":130,"skin":"ui/bg_exp.png","sizeGrid":"20,25,20,27","presetID":10,"name":"imgCoinBg","height":47},"compId":115,"child":[{"type":"Image","props":{"y":25,"x":9,"skin":"ui/icon_gold.png","presetID":11,"name":"imgCoin","anchorY":0.5,"anchorX":0.5},"compId":114},{"type":"Image","props":{"visible":false,"skin":"ui/bt_add.png","scaleY":0.4,"scaleX":0.4,"presetID":12,"name":"btnAddCoin","centerY":17,"centerX":-39,"anchorY":0.5,"anchorX":0.5},"compId":116},{"type":"Label","props":{"valign":"middle","text":"88888","strokeColor":"#cb3f19","stroke":2,"presetID":13,"name":"txtCoin","fontSize":28,"color":"#FFF","centerY":0,"centerX":13,"bold":true,"anchorY":0.5,"anchorX":0.5,"align":"center"},"compId":128},{"type":"Animation","props":{"y":38,"x":26,"source":"animation/notice.ani","presetID":23,"name":"coinNotice","autoPlay":true},"compId":147}]},{"type":"Image","props":{"y":20,"x":421,"width":130,"skin":"ui/bg_exp.png","sizeGrid":"20,25,20,27","presetID":14,"name":"imgDiamondBg","height":47},"compId":118,"child":[{"type":"Image","props":{"y":27,"x":15,"skin":"ui/icon_kim_cuong.png","presetID":15,"name":"imgDiamond","anchorY":0.5,"anchorX":0.5},"compId":117},{"type":"Image","props":{"visible":false,"skin":"ui/bt_add.png","scaleY":0.4,"scaleX":0.4,"presetID":16,"name":"btnAddDiamond","centerY":17,"centerX":-36,"anchorY":0.5,"anchorX":0.5},"compId":119},{"type":"Label","props":{"text":"888888","strokeColor":"#cb3f19","stroke":2,"presetID":17,"name":"txtDiamond","fontSize":22,"color":"#FFF","centerY":0,"centerX":16,"bold":true,"anchorY":0.5,"anchorX":0.5},"compId":129},{"type":"Animation","props":{"y":38,"x":26,"source":"animation/notice.ani","presetID":24,"name":"diamondNotice","autoPlay":true},"compId":148}]}],"loadList":["ui/img_circlebar1.png","animation/light_blue.ani","ui/img_circlebar3.png","ui/img_circlebar2.png","ui/icon_36_4_2.png","ui/bg_exp.png","ui/icon_22_4_1.png","ui/bt_add.png","ui/icon_gold.png","animation/notice.ani","ui/icon_kim_cuong.png"],"loadList3D":[]}